shishakai/__init__.py
shishakai/base.py
shishakai/moviewalker.py
shishakai-0.1.0.dist-info/LICENSE
shishakai-0.1.0.dist-info/WHEEL
shishakai-0.1.0.dist-info/METADATA
shishakai-0.1.0.dist-info/RECORD
